asgi_statik/__init__.py
asgi_statik/application.py
asgi_statik/config.py
asgi_statik/middleware.py
asgi_statik/responses/__init__.py
asgi_statik/responses/base.py
asgi_statik/responses/directory.py
asgi_statik/responses/file.py
asgi_statik/responses/static.py
asgi_statik/types.py
asgi_statik-0.1.0.dist-info/METADATA
asgi_statik-0.1.0.dist-info/WHEEL
asgi_statik-0.1.0.dist-info/RECORD
