Metadata-Version: 2.3
Name: asgi_statik
Version: 0.1.0
Summary: asgi_Statik is a high-performance, plug-and-play static file server for ASGI applications. Built for speed and simplicity, it seamlessly serves assets like HTML, CSS, JS, images, and more—without external dependencies or bulky middleware. Designed to fit naturally into async Python frameworks like Nexios, Statik gives you fine-grained control over file serving, cache headers, and MIME types—while keeping your stack minimal.
License: BSD-Clause-3
Keywords: static-files,asgi,file-server,async-python,static-assets,caching,compression,directory-listing,mime-types,spa-mode,streaming,etag,range-requests,security,performance,nexios
Author: Chidebele Dunamis
Author-email: techwithdunamix@gmail.com
Requires-Python: >=3.9
Classifier: License :: Other/Proprietary License
Classifier: Programming Language :: Python :: 3
Classifier: Programming Language :: Python :: 3.9
Classifier: Programming Language :: Python :: 3.10
Classifier: Programming Language :: Python :: 3.11
Classifier: Programming Language :: Python :: 3.12
Classifier: Programming Language :: Python :: 3.13
Requires-Dist: anyio (==4.9.0)
Requires-Dist: typing-extensions (==4.12.2)
Project-URL: Documentation, https://github.com/nexios-labs/statik/README.md
Project-URL: Homepage, https://github.com/nexios-labs/statik
Project-URL: Repository, https://github.com/nexios-labs/statik
